[
	{
		"name": "Blue_deckled",
		"author": "",
		"url": "https://raw.githubusercontent.com/matroniq/RollerduckBeta/master/Walls/Blue_deckled.png",
		"thumbnail": "https://raw.githubusercontent.com/matroniq/RollerduckBeta/master/Thumbs/Blue_deckled.png",
		"collections": "ABSTRACT",
		"downloadable": true,
		"size": 1703188,
		"dimensions": "1920 x 1920 px",
		"copyright": "© 2021 Rafael Murzabekov"
	},
	{
		"name": "Blue",
		"author": "",
		"url": "https://raw.githubusercontent.com/matroniq/RollerduckBeta/master/Walls/Blue.jpg",
		"thumbnail": "https://raw.githubusercontent.com/matroniq/RollerduckBeta/master/Thumbs/Blue.png",
		"collections": "ABSTRACT",
		"downloadable": true,
		"size": 384486,
		"dimensions": "1920 x 1920 px",
		"copyright": "© 2021 Rafael Murzabekov"
	},
	{
		"name": "Brush_deckled",
		"author": "",
		"url": "https://raw.githubusercontent.com/matroniq/RollerduckBeta/master/Walls/Brush_deckled.png",
		"thumbnail": "https://raw.githubusercontent.com/matroniq/RollerduckBeta/master/Thumbs/Brush_deckled.png",
		"collections": "ABSTRACT",
		"downloadable": true,
		"size": 1828983,
		"dimensions": "1920 x 1920 px",
		"copyright": "© 2021 Rafael Murzabekov"
	},
	{
		"name": "Brush",
		"author": "",
		"url": "https://raw.githubusercontent.com/matroniq/RollerduckBeta/master/Walls/Brush.jpg",
		"thumbnail": "https://raw.githubusercontent.com/matroniq/RollerduckBeta/master/Thumbs/Brush.png",
		"collections": "ABSTRACT",
		"downloadable": true,
		"size": 476742,
		"dimensions": "1920 x 1920 px",
		"copyright": "© 2021 Rafael Murzabekov"
	},
	{
		"name": "Honey_deckled",
		"author": "",
		"url": "https://raw.githubusercontent.com/matroniq/RollerduckBeta/master/Walls/Honey_deckled.png",
		"thumbnail": "https://raw.githubusercontent.com/matroniq/RollerduckBeta/master/Thumbs/Honey_deckled.png",
		"collections": "ABSTRACT",
		"downloadable": true,
		"size": 1730109,
		"dimensions": "1920 x 1920 px",
		"copyright": "© 2020 Rafael Murzabekov"
	},
	{
		"name": "Honey",
		"author": "",
		"url": "https://raw.githubusercontent.com/matroniq/RollerduckBeta/master/Walls/Honey.jpg",
		"thumbnail": "https://raw.githubusercontent.com/matroniq/RollerduckBeta/master/Thumbs/Honey.png",
		"collections": "ABSTRACT",
		"downloadable": true,
		"size": 668430,
		"dimensions": "1920 x 1920 px",
		"copyright": "© 2020 Rafael Murzabekov"
	},
	{
		"name": "Math_deckled",
		"author": "",
		"url": "https://raw.githubusercontent.com/matroniq/RollerduckBeta/master/Walls/Math_deckled.png",
		"thumbnail": "https://raw.githubusercontent.com/matroniq/RollerduckBeta/master/Thumbs/Math_deckled.png",
		"collections": "ABSTRACT",
		"downloadable": true,
		"size": 3040143,
		"dimensions": "1920 x 1920 px",
		"copyright": "© 2021 Rafael Murzabekov. Textures by onlygfx.com and wildtextures.com"
	},
	{
		"name": "Math",
		"author": "",
		"url": "https://raw.githubusercontent.com/matroniq/RollerduckBeta/master/Walls/Math.jpg",
		"thumbnail": "https://raw.githubusercontent.com/matroniq/RollerduckBeta/master/Thumbs/Math.png",
		"collections": "ABSTRACT",
		"downloadable": true,
		"size": 985442,
		"dimensions": "1920 x 1920 px",
		"copyright": "© 2021 Rafael Murzabekov. Textures by onlygfx.com and wildtextures.com"
	},
	{
		"name": "Milk_deckled",
		"author": "",
		"url": "https://raw.githubusercontent.com/matroniq/RollerduckBeta/master/Walls/Milk_deckled.png",
		"thumbnail": "https://raw.githubusercontent.com/matroniq/RollerduckBeta/master/Thumbs/Milk_deckled.png",
		"collections": "ABSTRACT",
		"downloadable": true,
		"size": 1933192,
		"dimensions": "1920 x 1920 px",
		"copyright": "© 2020 Rafael Murzabekov"
	},
	{
		"name": "Milk",
		"author": "",
		"url": "https://raw.githubusercontent.com/matroniq/RollerduckBeta/master/Walls/Milk.jpg",
		"thumbnail": "https://raw.githubusercontent.com/matroniq/RollerduckBeta/master/Thumbs/Milk.png",
		"collections": "ABSTRACT",
		"downloadable": true,
		"size": 702865,
		"dimensions": "1920 x 1920 px",
		"copyright": "© 2020 Rafael Murzabekov"
	},
	{
		"name": "Petroglyph1_deckled",
		"author": "",
		"url": "https://raw.githubusercontent.com/matroniq/RollerduckBeta/master/Walls/Petroglyph1_deckled.png",
		"thumbnail": "https://raw.githubusercontent.com/matroniq/RollerduckBeta/master/Thumbs/Petroglyph1_deckled.png",
		"collections": "ABSTRACT",
		"downloadable": true,
		"size": 1481787,
		"dimensions": "1920 x 1920 px",
		"copyright": "© 2021 Rafael Murzabekov"
	},
	{
		"name": "Petroglyph1",
		"author": "",
		"url": "https://raw.githubusercontent.com/matroniq/RollerduckBeta/master/Walls/Petroglyph1.jpg",
		"thumbnail": "https://raw.githubusercontent.com/matroniq/RollerduckBeta/master/Thumbs/Petroglyph1.png",
		"collections": "ABSTRACT",
		"downloadable": true,
		"size": 637216,
		"dimensions": "1920 x 1920 px",
		"copyright": "© 2021 Rafael Murzabekov"
	},
	{
		"name": "Petroglyph2_deckled",
		"author": "",
		"url": "https://raw.githubusercontent.com/matroniq/RollerduckBeta/master/Walls/Petroglyph2_deckled.png",
		"thumbnail": "https://raw.githubusercontent.com/matroniq/RollerduckBeta/master/Thumbs/Petroglyph2_deckled.png",
		"collections": "ABSTRACT",
		"downloadable": true,
		"size": 2700761,
		"dimensions": "1920 x 1920 px",
		"copyright": "© 2021 Rafael Murzabekov"
	},
	{
		"name": "Petroglyph2",
		"author": "",
		"url": "https://raw.githubusercontent.com/matroniq/RollerduckBeta/master/Walls/Petroglyph2.jpg",
		"thumbnail": "https://raw.githubusercontent.com/matroniq/RollerduckBeta/master/Thumbs/Petroglyph2.png",
		"collections": "ABSTRACT",
		"downloadable": true,
		"size": 841776,
		"dimensions": "1920 x 1920 px",
		"copyright": "© 2021 Rafael Murzabekov"
	},
	{
		"name": "Petroglyph3_deckled",
		"author": "",
		"url": "https://raw.githubusercontent.com/matroniq/RollerduckBeta/master/Walls/Petroglyph3_deckled.png",
		"thumbnail": "https://raw.githubusercontent.com/matroniq/RollerduckBeta/master/Thumbs/Petroglyph3_deckled.png",
		"collections": "ABSTRACT",
		"downloadable": true,
		"size": 2797944,
		"dimensions": "1920 x 1920 px",
		"copyright": "© 2021 Rafael Murzabekov"
	},
	{
		"name": "Petroglyph3",
		"author": "",
		"url": "https://raw.githubusercontent.com/matroniq/RollerduckBeta/master/Walls/Petroglyph3.jpg",
		"thumbnail": "https://raw.githubusercontent.com/matroniq/RollerduckBeta/master/Thumbs/Petroglyph3.png",
		"collections": "ABSTRACT",
		"downloadable": true,
		"size": 837899,
		"dimensions": "1920 x 1920 px",
		"copyright": "© 2021 Rafael Murzabekov"
	},
	{
		"name": "Rock_deckled",
		"author": "",
		"url": "https://raw.githubusercontent.com/matroniq/RollerduckBeta/master/Walls/Rock_deckled.png",
		"thumbnail": "https://raw.githubusercontent.com/matroniq/RollerduckBeta/master/Thumbs/Rock_deckled.png",
		"collections": "ABSTRACT",
		"downloadable": true,
		"size": 2323646,
		"dimensions": "1920 x 1920 px",
		"copyright": "© 2021 Rafael Murzabekov"
	},
	{
		"name": "Rock",
		"author": "",
		"url": "https://raw.githubusercontent.com/matroniq/RollerduckBeta/master/Walls/Rock.jpg",
		"thumbnail": "https://raw.githubusercontent.com/matroniq/RollerduckBeta/master/Thumbs/Rock.png",
		"collections": "ABSTRACT",
		"downloadable": true,
		"size": 798997,
		"dimensions": "1920 x 1920 px",
		"copyright": "© 2021 Rafael Murzabekov"
	},
	{
		"name": "Rock2_deckled",
		"author": "",
		"url": "https://raw.githubusercontent.com/matroniq/RollerduckBeta/master/Walls/Rock2_deckled.png",
		"thumbnail": "https://raw.githubusercontent.com/matroniq/RollerduckBeta/master/Thumbs/Rock2_deckled.png",
		"collections": "ABSTRACT",
		"downloadable": true,
		"size": 2201426,
		"dimensions": "1920 x 1920 px",
		"copyright": "© 2021 Rafael Murzabekov"
	},
	{
		"name": "Rock2",
		"author": "",
		"url": "https://raw.githubusercontent.com/matroniq/RollerduckBeta/master/Walls/Rock2.jpg",
		"thumbnail": "https://raw.githubusercontent.com/matroniq/RollerduckBeta/master/Thumbs/Rock2.png",
		"collections": "ABSTRACT",
		"downloadable": true,
		"size": 913640,
		"dimensions": "1920 x 1920 px",
		"copyright": "© 2021 Rafael Murzabekov"
	},
	{
		"name": "Tree_deckled",
		"author": "",
		"url": "https://raw.githubusercontent.com/matroniq/RollerduckBeta/master/Walls/Tree_deckled.png",
		"thumbnail": "https://raw.githubusercontent.com/matroniq/RollerduckBeta/master/Thumbs/Tree_deckled.png",
		"collections": "ABSTRACT",
		"downloadable": true,
		"size": 2806453,
		"dimensions": "1920 x 1920 px",
		"copyright": "© 2021 Rafael Murzabekov. Textures by onlygfx.com"
	},
	{
		"name": "Tree",
		"author": "",
		"url": "https://raw.githubusercontent.com/matroniq/RollerduckBeta/master/Walls/Tree.jpg",
		"thumbnail": "https://raw.githubusercontent.com/matroniq/RollerduckBeta/master/Thumbs/Tree.png",
		"collections": "ABSTRACT",
		"downloadable": true,
		"size": 809718,
		"dimensions": "1920 x 1920 px",
		"copyright": "© 2021 Rafael Murzabekov. Textures by onlygfx.com"
	}
	{
		"name": "Canvas1_deckled",
		"author": "",
		"url": "https://raw.githubusercontent.com/matroniq/RollerduckBeta/master/Walls/Canvas1_deckled.png",
		"thumbnail": "https://raw.githubusercontent.com/matroniq/RollerduckBeta/master/Thumbs/Canvas1_deckled.png",
		"collections": "CANVAS",
		"downloadable": true,
		"size": 1549170,
		"dimensions": "1920 x 1920 px",
		"copyright": "© 2020 Rafael Murzabekov"
	},
	{
		"name": "Canvas1",
		"author": "",
		"url": "https://raw.githubusercontent.com/matroniq/RollerduckBeta/master/Walls/Canvas1.jpg",
		"thumbnail": "https://raw.githubusercontent.com/matroniq/RollerduckBeta/master/Thumbs/Canvas1.png",
		"collections": "CANVAS",
		"downloadable": true,
		"size": 271263,
		"dimensions": "1920 x 1920 px",
		"copyright": "© 2020 Rafael Murzabekov"
	},
	{
		"name": "Canvas2_deckled",
		"author": "",
		"url": "https://raw.githubusercontent.com/matroniq/RollerduckBeta/master/Walls/Canvas2_deckled.png",
		"thumbnail": "https://raw.githubusercontent.com/matroniq/RollerduckBeta/master/Thumbs/Canvas2_deckled.png",
		"collections": "CANVAS",
		"downloadable": true,
		"size": 1104179,
		"dimensions": "1920 x 1920 px",
		"copyright": "© 2020 Rafael Murzabekov"
	},
	{
		"name": "Canvas2",
		"author": "",
		"url": "https://raw.githubusercontent.com/matroniq/RollerduckBeta/master/Walls/Canvas2.jpg",
		"thumbnail": "https://raw.githubusercontent.com/matroniq/RollerduckBeta/master/Thumbs/Canvas2.png",
		"collections": "CANVAS",
		"downloadable": true,
		"size": 210622,
		"dimensions": "1920 x 1920 px",
		"copyright": "© 2020 Rafael Murzabekov"
	},
	{
		"name": "Canvas3_deckled",
		"author": "",
		"url": "https://raw.githubusercontent.com/matroniq/RollerduckBeta/master/Walls/Canvas3_deckled.png",
		"thumbnail": "https://raw.githubusercontent.com/matroniq/RollerduckBeta/master/Thumbs/Canvas3_deckled.png",
		"collections": "CANVAS",
		"downloadable": true,
		"size": 1312147,
		"dimensions": "1920 x 1920 px",
		"copyright": "© 2020 Rafael Murzabekov"
	},
	{
		"name": "Canvas3",
		"author": "",
		"url": "https://raw.githubusercontent.com/matroniq/RollerduckBeta/master/Walls/Canvas3.jpg",
		"thumbnail": "https://raw.githubusercontent.com/matroniq/RollerduckBeta/master/Thumbs/Canvas3.png",
		"collections": "CANVAS",
		"downloadable": true,
		"size": 201438,
		"dimensions": "1920 x 1920 px",
		"copyright": "© 2020 Rafael Murzabekov"
	},
	{
		"name": "Canvas4_deckled",
		"author": "",
		"url": "https://raw.githubusercontent.com/matroniq/RollerduckBeta/master/Walls/Canvas4_deckled.png",
		"thumbnail": "https://raw.githubusercontent.com/matroniq/RollerduckBeta/master/Thumbs/Canvas4_deckled.png",
		"collections": "CANVAS",
		"downloadable": true,
		"size": 1651563,
		"dimensions": "1920 x 1920 px",
		"copyright": "© 2020 Rafael Murzabekov"
	},
	{
		"name": "Canvas4",
		"author": "",
		"url": "https://raw.githubusercontent.com/matroniq/RollerduckBeta/master/Walls/Canvas4.jpg",
		"thumbnail": "https://raw.githubusercontent.com/matroniq/RollerduckBeta/master/Thumbs/Canvas4.png",
		"collections": "CANVAS",
		"downloadable": true,
		"size": 258474,
		"dimensions": "1920 x 1920 px",
		"copyright": "© 2020 Rafael Murzabekov"
	},
	{
		"name": "Canvas5_deckled",
		"author": "",
		"url": "https://raw.githubusercontent.com/matroniq/RollerduckBeta/master/Walls/Canvas5_deckled.png",
		"thumbnail": "https://raw.githubusercontent.com/matroniq/RollerduckBeta/master/Thumbs/Canvas5_deckled.png",
		"collections": "CANVAS",
		"downloadable": true,
		"size": 1264575,
		"dimensions": "1920 x 1920 px",
		"copyright": "© 2020 Rafael Murzabekov"
	},
	{
		"name": "Canvas5",
		"author": "",
		"url": "https://raw.githubusercontent.com/matroniq/RollerduckBeta/master/Walls/Canvas5.jpg",
		"thumbnail": "https://raw.githubusercontent.com/matroniq/RollerduckBeta/master/Thumbs/Canvas5.png",
		"collections": "CANVAS",
		"downloadable": true,
		"size": 200360,
		"dimensions": "1920 x 1920 px",
		"copyright": "© 2020 Rafael Murzabekov"
	},
	{
		"name": "Canvas6_deckled",
		"author": "",
		"url": "https://raw.githubusercontent.com/matroniq/RollerduckBeta/master/Walls/Canvas6_deckled.png",
		"thumbnail": "https://raw.githubusercontent.com/matroniq/RollerduckBeta/master/Thumbs/Canvas6_deckled.png",
		"collections": "CANVAS",
		"downloadable": true,
		"size": 1608853,
		"dimensions": "1920 x 1920 px",
		"copyright": "© 2020 Rafael Murzabekov"
	},
	{
		"name": "Canvas6",
		"author": "",
		"url": "https://raw.githubusercontent.com/matroniq/RollerduckBeta/master/Walls/Canvas6.jpg",
		"thumbnail": "https://raw.githubusercontent.com/matroniq/RollerduckBeta/master/Thumbs/Canvas6.png",
		"collections": "CANVAS",
		"downloadable": true,
		"size": 258033,
		"dimensions": "1920 x 1920 px",
		"copyright": "© 2020 Rafael Murzabekov"
	},
	{
		"name": "Canvas7_deckled",
		"author": "",
		"url": "https://raw.githubusercontent.com/matroniq/RollerduckBeta/master/Walls/Canvas7_deckled.png",
		"thumbnail": "https://raw.githubusercontent.com/matroniq/RollerduckBeta/master/Thumbs/Canvas7_deckled.png",
		"collections": "CANVAS",
		"downloadable": true,
		"size": 1415066,
		"dimensions": "1920 x 1920 px",
		"copyright": "© 2020 Rafael Murzabekov"
	},
	{
		"name": "Canvas7",
		"author": "",
		"url": "https://raw.githubusercontent.com/matroniq/RollerduckBeta/master/Walls/Canvas7.jpg",
		"thumbnail": "https://raw.githubusercontent.com/matroniq/RollerduckBeta/master/Thumbs/Canvas7.png",
		"collections": "CANVAS",
		"downloadable": true,
		"size": 267053,
		"dimensions": "1920 x 1920 px",
		"copyright": "© 2020 Rafael Murzabekov"
	},
	{
		"name": "Canvas8_deckled",
		"author": "",
		"url": "https://raw.githubusercontent.com/matroniq/RollerduckBeta/master/Walls/Canvas8_deckled.png",
		"thumbnail": "https://raw.githubusercontent.com/matroniq/RollerduckBeta/master/Thumbs/Canvas8_deckled.png",
		"collections": "CANVAS",
		"downloadable": true,
		"size": 793428,
		"dimensions": "1920 x 1920 px",
		"copyright": "© 2020 Rafael Murzabekov"
	},
	{
		"name": "Canvas8",
		"author": "",
		"url": "https://raw.githubusercontent.com/matroniq/RollerduckBeta/master/Walls/Canvas8.jpg",
		"thumbnail": "https://raw.githubusercontent.com/matroniq/RollerduckBeta/master/Thumbs/Canvas8.png",
		"collections": "CANVAS",
		"downloadable": true,
		"size": 251195,
		"dimensions": "1920 x 1920 px",
		"copyright": "© 2020 Rafael Murzabekov"
	},
]
